.bumpversion.cfg
.cookiecutterrc
.coveragerc
.editorconfig
.travis.yml
AUTHORS.rst
CHANGELOG.rst
CONTRIBUTING.rst
LICENSE
MANIFEST.in
README.rst
appveyor.yml
setup.cfg
setup.py
tox.ini
ci/appveyor-bootstrap.py
ci/appveyor-download.py
ci/appveyor-with-compiler.cmd
ci/bootstrap.py
ci/templates/.travis.yml
ci/templates/appveyor.yml
docs/authors.rst
docs/changelog.rst
docs/conf.py
docs/contributing.rst
docs/index.rst
docs/installation.rst
docs/readme.rst
docs/requirements.txt
docs/spelling_wordlist.txt
docs/usage.rst
docs/reference/index.rst
docs/reference/pytrello.rst
src/pytrello/__init__.py
src/pytrello/__main__.py
src/pytrello/cli.py
src/pytrello/decorators.py
src/pytrello/request_wrapper.py
src/pytrello.egg-info/PKG-INFO
src/pytrello.egg-info/SOURCES.txt
src/pytrello.egg-info/dependency_links.txt
src/pytrello.egg-info/entry_points.txt
src/pytrello.egg-info/not-zip-safe
src/pytrello.egg-info/requires.txt
src/pytrello.egg-info/top_level.txt
src/pytrello/api/__init__.py
src/pytrello/api/api.yaml
src/pytrello/api/board.py
src/pytrello/api/card.py
src/pytrello/api/decorators.py
src/pytrello/api/label.py
src/pytrello/api/util.py
tests/test_board_api.py
tests/test_pytrello.py